ProcBigEasyDriver/ProcBigEasyDriver.py
ProcBigEasyDriver/__init__.py
ProcBigEasyDriver-0.0.3.dist-info/LICENSE
ProcBigEasyDriver-0.0.3.dist-info/METADATA
ProcBigEasyDriver-0.0.3.dist-info/WHEEL
ProcBigEasyDriver-0.0.3.dist-info/top_level.txt
ProcBigEasyDriver-0.0.3.dist-info/RECORD
