Metadata-Version: 2.1
Name: ProcBigEasyDriver
Version: 0.0.3
Summary: PI controller for continously rotating a stepper using the big easy driver in a background process on RPi
Home-page: https://github.com/mattisabrat/Processed_PI_BigEasyDriver
Author: Matthew Davenport
Author-email: mdavenport@rockefeller.edu
License: GPLv3
Platform: UNKNOWN
Classifier: Development Status :: 3 - Alpha
Classifier: License :: OSI Approved :: GNU General Public License v3 (GPLv3)
Classifier: Programming Language :: Python :: 3 :: Only
Classifier: Operating System :: POSIX :: Linux
Requires-Dist: gpiozero
Requires-Dist: pigpio
Requires-Dist: rpi-gpio
